{"inkVersion":20,"root":[["^REWOLWER: Czołem compadre! Dość już się należałem na tym stoliku.","\n","^Podnieś mnie i ruszamy.","\n","^Z moim mózgiem i Twoim, czymś ... zawojujemy świat. ",{"->":"1a"},"\n",["done",{"#f":5,"#n":"g-0"}],null],"done",{"1a":[["^...","\n","^REWOLWER: Potrafię wiele, ale najchętniej robię dziury w rzeczach.","\n","ev","str","^kontynuuj...","/str","/ev",{"*":".^.c-0","flg":20},{"c-0":["^ ",{"->":"2b"},"\n",{"#f":5}]}],{"#f":1}],"2b":[["^LUSTERKO: Po prostu wyceluj i strzel (lewy przycisk myszki)","\n","ev","str","^kontynuuj...","/str","/ev",{"*":".^.c-0","flg":20},{"c-0":[{"->":"2c"},"\n",{"#f":5}]}],{"#f":1}],"2c":[["^REWOLWER: Jeśli coś jest poza Twoim zasięgiem musisz pogłówkować.","\n","^Poszukaj świecących się powierzchni i umieść w nich kulkę.","\n","^(rykoszetuj od świecących kwadratów)","\n","ev","str","^JD: weź rewolwer i go ugryź","/str","/ev",{"*":".^.c-0","flg":20},"ev","str","^JD: weź rewolwer i strzel w powietrze","/str","/ev",{"*":".^.c-1","flg":20},{"c-0":["^ ",{"->":"2d"},"\n",{"#f":5}],"c-1":["^ ",{"->":"2d"},"\n",{"#f":5}]}],{"#f":1}],"2d":["^REWOLWER: Dobrze kolego. Ruszamy! Witaj świecie!","\n","^O tam coś jest. Strzel do tych łańcuchów!","\n","done",{"#f":1}],"#f":1}],"listDefs":{}}